base/__init__.py
base/base_object.py
base/singleton.py
database/__init__.py
database/base_dao.py
database/connect_pool.py
database/transaction.py
decorator/__init__.py
decorator/retry.py
error/__init__.py
error/error.py
factory/__init__.py
factory/factory.py
factory/register.py
test/__init__.py
test/util/__init__.py
test/util/test_file_util.py
util/__init__.py
util/collection_util.py
util/digest_util.py
util/file_util.py
util/func_util.py
util/html_util.py
util/http_util.py
util/image_util.py
util/log_util.py
util/module_util.py
util/number_util.py
util/object_util.py
util/path_util.py
util/prometheus_util.py
util/string_util.py
util/time_util.py
util/url_util.py
util/xml_util.py
icemammoth_common-0.1.0.dist-info/METADATA
icemammoth_common-0.1.0.dist-info/WHEEL
icemammoth_common-0.1.0.dist-info/top_level.txt
icemammoth_common-0.1.0.dist-info/RECORD
