Metadata-Version: 2.1
Name: icemammoth_common
Version: 0.1.0
Summary: common tools collection
Home-page: 
Author: Klein
Author-email: myicemammoth@gmail.com
Keywords: common utils
Classifier: Development Status :: 3 - Alpha
Classifier: Intended Audience :: Developers
Classifier: License :: OSI Approved :: MIT License
Classifier: Programming Language :: Python :: 3.12
Requires-Dist: beautifulsoup4 >=4.12.3
Requires-Dist: coloredlogs >=15.0.1
Requires-Dist: mysql-connector-repackaged >=0.3.1
Requires-Dist: Pillow >=10.3.0
Requires-Dist: Requests >=2.32.2
